<?xml version="1.0" encoding="utf-8"?>
<company name="Brainbox" address="783 Basil Drive" uuid="717536533">
  <stores>
    <store name="Youbridge" address="042 Red Cloud Center">
      <receipts>
        <receipt>
          <total>532.4</total>
          <datetime>2019-10-09T16:28:00</datetime>
          <payment>cash</payment>
        </receipt>
        <receipt>
          <total>4386.78</total>
          <datetime>2019-10-09T13:19:00</datetime>
          <payment>card</payment>
          <carddetails>
            <cardtype>americanexpress</cardtype>
            <number>372301106242391</number>
            <contactless>false</contactless>
          </carddetails>
        </receipt>
        <receipt>
          <total>3300.23</total>
          <datetime>2019-10-09T16:26:00</datetime>
          <payment>card</payment>
          <carddetails>
            <cardtype>americanexpress</cardtype>
            <number>374283168711364</number>
            <contactless>false</contactless>
          </carddetails>
        </receipt>
        <receipt>
          <total>4727.36</total>
          <datetime>2019-10-09T11:23:00</datetime>
          <payment>cash</payment>
        </receipt>
        <receipt>
          <total>3664.92</total>
          <datetime>2019-10-09T13:58:00</datetime>
          <payment>card</payment>
          <carddetails>
            <cardtype>china-unionpay</cardtype>
            <number>560221180197325646</number>
            <contactless>true</contactless>
          </carddetails>
        </receipt>
        <receipt>
          <total>9017.11</total>
          <datetime>2019-10-09T13:04:00</datetime>
          <payment>card</payment>
          <carddetails>
            <cardtype>mastercard</cardtype>
            <number>5100132720929222</number>
            <contactless>false</contactless>
          </carddetails>
        </receipt>
        <receipt>
          <total>3085.3</total>
          <datetime>2019-10-09T10:01:00</datetime>
          <payment>card</payment>
          <carddetails>
            <cardtype>jcb</cardtype>
            <number>3583242715707318</number>
            <contactless>true</contactless>
          </carddetails>
        </receipt>
        <receipt>
          <total>6633.59</total>
          <datetime>2019-10-09T16:13:00</datetime>
          <payment>card</payment>
          <carddetails>
            <cardtype>jcb</cardtype>
            <number>3547901516845586</number>
            <contactless>false</contactless>
          </carddetails>
        </receipt>
        <receipt>
          <total>9580.57</total>
          <datetime>2019-10-09T10:33:00</datetime>
          <payment>cash</payment>
        </receipt>
        <receipt>
          <total>9360.66</total>
          <datetime>2019-10-09T14:34:00</datetime>
          <payment>cash</payment>
        </receipt>
      </receipts>
      <invoices>
        <invoice>
          <total>81717.65</total>
          <datetime>2019-10-09T11:08:00</datetime>
          <customer>
            <name>Feedmix</name>
            <address>9621 Spenser Alley</address>
            <uuid>839249696</uuid>
          </customer>
          <payment>cash</payment>
        </invoice>
        <invoice>
          <total>71437.96</total>
          <datetime>2019-10-09T10:49:00</datetime>
          <customer>
            <name>Jabbersphere</name>
            <address>564 Glendale Terrace</address>
            <uuid>511790124</uuid>
          </customer>
          <payment>cash</payment>
        </invoice>
        <invoice>
          <total>82037.59</total>
          <datetime>2019-10-09T16:55:00</datetime>
          <customer>
            <name>Centimia</name>
            <address>25 Manitowish Road</address>
            <uuid>441046281</uuid>
          </customer>
          <payment>cash</payment>
        </invoice>
        <invoice>
          <total>51015.44</total>
          <datetime>2019-10-09T17:55:00</datetime>
          <customer>
            <name>Innojam</name>
            <address>35190 Northridge Street</address>
            <uuid>445132775</uuid>
          </customer>
          <payment>card</payment>
          <carddetails>
            <cardtype>diners-club-carte-blanche</cardtype>
            <number>30186256224552</number>
            <contactless>true</contactless>
          </carddetails>
        </invoice>
        <invoice>
          <total>92994.95</total>
          <datetime>2019-10-09T14:22:00</datetime>
          <customer>
            <name>Leenti</name>
            <address>9953 Longview Drive</address>
            <uuid>924252694</uuid>
          </customer>
          <payment>cash</payment>
        </invoice>
        <invoice>
          <total>30236.13</total>
          <datetime>2019-10-09T07:57:00</datetime>
          <customer>
            <name>Photolist</name>
            <address>183 Bellgrove Court</address>
            <uuid>138147292</uuid>
          </customer>
          <payment>card</payment>
          <carddetails>
            <cardtype>jcb</cardtype>
            <number>3533760674002802</number>
            <contactless>true</contactless>
          </carddetails>
        </invoice>
        <invoice>
          <total>65829.86</total>
          <datetime>2019-10-09T17:49:00</datetime>
          <customer>
            <name>Buzzbean</name>
            <address>86 Cascade Hill</address>
            <uuid>385635315</uuid>
          </customer>
          <payment>card</payment>
          <carddetails>
            <cardtype>jcb</cardtype>
            <number>3547901516845586</number>
            <contactless>false</contactless>
          </carddetails>
        </invoice>
        <invoice>
          <total>99885.99</total>
          <datetime>2019-10-09T16:14:00</datetime>
          <customer>
            <name>Innojam</name>
            <address>35190 Northridge Street</address>
            <uuid>445132775</uuid>
          </customer>
          <payment>cash</payment>
        </invoice>
      </invoices>
    </store>
    <store name="Quimm" address="5 Cody Road">
      <receipts>
        <receipt>
          <total>2607.46</total>
          <datetime>2019-10-09T11:02:00</datetime>
          <payment>cash</payment>
        </receipt>
        <receipt>
          <total>5561.47</total>
          <datetime>2019-10-09T12:10:00</datetime>
          <payment>card</payment>
          <carddetails>
            <cardtype>jcb</cardtype>
            <number>3540564668810266</number>
            <contactless>false</contactless>
          </carddetails>
        </receipt>
        <receipt>
          <total>7115.54</total>
          <datetime>2019-10-09T17:56:00</datetime>
          <payment>card</payment>
          <carddetails>
            <cardtype>jcb</cardtype>
            <number>3539938882798049</number>
            <contactless>true</contactless>
          </carddetails>
        </receipt>
        <receipt>
          <total>9909.17</total>
          <datetime>2019-10-09T15:38:00</datetime>
          <payment>cash</payment>
        </receipt>
        <receipt>
          <total>3758.85</total>
          <datetime>2019-10-09T16:57:00</datetime>
          <payment>cash</payment>
        </receipt>
        <receipt>
          <total>3869.72</total>
          <datetime>2019-10-09T13:50:00</datetime>
          <payment>cash</payment>
        </receipt>
        <receipt>
          <total>4926.91</total>
          <datetime>2019-10-09T10:19:00</datetime>
          <payment>cash</payment>
        </receipt>
        <receipt>
          <total>4257.67</total>
          <datetime>2019-10-09T17:07:00</datetime>
          <payment>cash</payment>
        </receipt>
        <receipt>
          <total>2917.48</total>
          <datetime>2019-10-09T09:49:00</datetime>
          <payment>cash</payment>
        </receipt>
        <receipt>
          <total>4658.33</total>
          <datetime>2019-10-09T12:08:00</datetime>
          <payment>card</payment>
          <carddetails>
            <cardtype>bankcard</cardtype>
            <number>5602210815994930</number>
            <contactless>true</contactless>
          </carddetails>
        </receipt>
      </receipts>
      <invoices>
        <invoice>
          <total>88672.15</total>
          <datetime>2019-10-09T15:09:00</datetime>
          <customer>
            <name>Devpulse</name>
            <address>651 Prentice Place</address>
            <uuid>970330488</uuid>
          </customer>
          <payment>cash</payment>
        </invoice>
        <invoice>
          <total>46491.96</total>
          <datetime>2019-10-09T07:44:00</datetime>
          <customer>
            <name>Topicshots</name>
            <address>4 Spenser Pass</address>
            <uuid>789815946</uuid>
          </customer>
          <payment>cash</payment>
        </invoice>
        <invoice>
          <total>18786.73</total>
          <datetime>2019-10-09T08:27:00</datetime>
          <customer>
            <name>Livefish</name>
            <address>15943 Summer Ridge Court</address>
            <uuid>177723307</uuid>
          </customer>
          <payment>card</payment>
          <carddetails>
            <cardtype>jcb</cardtype>
            <number>3578623947075599</number>
            <contactless>false</contactless>
          </carddetails>
        </invoice>
        <invoice>
          <total>16295.75</total>
          <datetime>2019-10-09T10:43:00</datetime>
          <customer>
            <name>Voomm</name>
            <address>47 Canary Point</address>
            <uuid>472412956</uuid>
          </customer>
          <payment>card</payment>
          <carddetails>
            <cardtype>diners-club-carte-blanche</cardtype>
            <number>30348205866442</number>
            <contactless>true</contactless>
          </carddetails>
        </invoice>
        <invoice>
          <total>14915.25</total>
          <datetime>2019-10-09T11:35:00</datetime>
          <customer>
            <name>Fiveclub</name>
            <address>085 Grayhawk Lane</address>
            <uuid>432573080</uuid>
          </customer>
          <payment>card</payment>
          <carddetails>
            <cardtype>jcb</cardtype>
            <number>3554055080602111</number>
            <contactless>false</contactless>
          </carddetails>
        </invoice>
        <invoice>
          <total>60349.49</total>
          <datetime>2019-10-09T06:35:00</datetime>
          <customer>
            <name>Izio</name>
            <address>57 Esker Circle</address>
            <uuid>981958422</uuid>
          </customer>
          <payment>cash</payment>
        </invoice>
        <invoice>
          <total>85801.29</total>
          <datetime>2019-10-09T12:26:00</datetime>
          <customer>
            <name>Fivechat</name>
            <address>397 Pleasure Way</address>
            <uuid>715184091</uuid>
          </customer>
          <payment>card</payment>
          <carddetails>
            <cardtype>jcb</cardtype>
            <number>3587591975201024</number>
            <contactless>false</contactless>
          </carddetails>
        </invoice>
        <invoice>
          <total>34255.19</total>
          <datetime>2019-10-09T11:29:00</datetime>
          <customer>
            <name>Fiveclub</name>
            <address>085 Grayhawk Lane</address>
            <uuid>432573080</uuid>
          </customer>
          <payment>card</payment>
          <carddetails>
            <cardtype>china-unionpay</cardtype>
            <number>560221180197325646</number>
            <contactless>true</contactless>
          </carddetails>
        </invoice>
      </invoices>
    </store>
  </stores>
</company>