<?xml version="1.0" encoding="utf-8"?>
<company name="Rhynyx" address="0808 Knutson Road" uuid="516442312">
  <stores>
    <store name="Quinu" address="46 Acker Street">
      <receipts>
        <receipt>
          <total>6435.13</total>
          <datetime>2019-09-13T17:33:00</datetime>
          <payment>card</payment>
          <carddetails>
            <cardtype>diners-club-carte-blanche</cardtype>
            <number>30348205866442</number>
            <contactless>true</contactless>
          </carddetails>
        </receipt>
        <receipt>
          <total>5076.7</total>
          <datetime>2019-09-13T16:18:00</datetime>
          <payment>cash</payment>
        </receipt>
        <receipt>
          <total>2288.71</total>
          <datetime>2019-09-13T16:02:00</datetime>
          <payment>card</payment>
          <carddetails>
            <cardtype>mastercard</cardtype>
            <number>5396231484697810</number>
            <contactless>false</contactless>
          </carddetails>
        </receipt>
        <receipt>
          <total>2143.22</total>
          <datetime>2019-09-13T10:07:00</datetime>
          <payment>card</payment>
          <carddetails>
            <cardtype>mastercard</cardtype>
            <number>5396231484697810</number>
            <contactless>false</contactless>
          </carddetails>
        </receipt>
        <receipt>
          <total>6166.5</total>
          <datetime>2019-09-13T13:23:00</datetime>
          <payment>card</payment>
          <carddetails>
            <cardtype>diners-club-us-ca</cardtype>
            <number>5419906721807495</number>
            <contactless>true</contactless>
          </carddetails>
        </receipt>
        <receipt>
          <total>3785.47</total>
          <datetime>2019-09-13T15:14:00</datetime>
          <payment>cash</payment>
        </receipt>
        <receipt>
          <total>6872.35</total>
          <datetime>2019-09-13T11:22:00</datetime>
          <payment>card</payment>
          <carddetails>
            <cardtype>jcb</cardtype>
            <number>3557227819051392</number>
            <contactless>true</contactless>
          </carddetails>
        </receipt>
        <receipt>
          <total>2105.12</total>
          <datetime>2019-09-13T10:38:00</datetime>
          <payment>card</payment>
          <carddetails>
            <cardtype>mastercard</cardtype>
            <number>5100132720929222</number>
            <contactless>false</contactless>
          </carddetails>
        </receipt>
        <receipt>
          <total>9457.82</total>
          <datetime>2019-09-13T15:44:00</datetime>
          <payment>cash</payment>
        </receipt>
        <receipt>
          <total>5178.73</total>
          <datetime>2019-09-13T11:10:00</datetime>
          <payment>cash</payment>
        </receipt>
        <receipt>
          <total>8594.66</total>
          <datetime>2019-09-13T09:24:00</datetime>
          <payment>cash</payment>
        </receipt>
        <receipt>
          <total>2139.16</total>
          <datetime>2019-09-13T15:41:00</datetime>
          <payment>cash</payment>
        </receipt>
      </receipts>
      <invoices>
        <invoice>
          <total>44019.62</total>
          <datetime>2019-09-13T14:10:00</datetime>
          <customer>
            <name>Photolist</name>
            <address>183 Bellgrove Court</address>
            <uuid>138147292</uuid>
          </customer>
          <payment>cash</payment>
        </invoice>
        <invoice>
          <total>12947.4</total>
          <datetime>2019-09-13T08:55:00</datetime>
          <customer>
            <name>Jazzy</name>
            <address>8716 Prairie Rose Place</address>
            <uuid>905960616</uuid>
          </customer>
          <payment>card</payment>
          <carddetails>
            <cardtype>mastercard</cardtype>
            <number>5384821848019398</number>
            <contactless>true</contactless>
          </carddetails>
        </invoice>
        <invoice>
          <total>31900.54</total>
          <datetime>2019-09-13T08:38:00</datetime>
          <customer>
            <name>Realcube</name>
            <address>00 Maple Trail</address>
            <uuid>812703107</uuid>
          </customer>
          <payment>cash</payment>
        </invoice>
        <invoice>
          <total>23256.76</total>
          <datetime>2019-09-13T13:26:00</datetime>
          <customer>
            <name>Izio</name>
            <address>57 Esker Circle</address>
            <uuid>981958422</uuid>
          </customer>
          <payment>cash</payment>
        </invoice>
        <invoice>
          <total>77881.07</total>
          <datetime>2019-09-13T14:38:00</datetime>
          <customer>
            <name>Einti</name>
            <address>122 Grim Center</address>
            <uuid>947802486</uuid>
          </customer>
          <payment>cash</payment>
        </invoice>
        <invoice>
          <total>20438.46</total>
          <datetime>2019-09-13T13:26:00</datetime>
          <customer>
            <name>Blognation</name>
            <address>627 Nova Way</address>
            <uuid>722497529</uuid>
          </customer>
          <payment>card</payment>
          <carddetails>
            <cardtype>visa-electron</cardtype>
            <number>4844762213017681</number>
            <contactless>false</contactless>
          </carddetails>
        </invoice>
        <invoice>
          <total>16679.86</total>
          <datetime>2019-09-13T17:31:00</datetime>
          <customer>
            <name>Buzzbean</name>
            <address>86 Cascade Hill</address>
            <uuid>385635315</uuid>
          </customer>
          <payment>card</payment>
          <carddetails>
            <cardtype>diners-club-carte-blanche</cardtype>
            <number>30186256224552</number>
            <contactless>true</contactless>
          </carddetails>
        </invoice>
        <invoice>
          <total>77869.69</total>
          <datetime>2019-09-13T10:43:00</datetime>
          <customer>
            <name>Voomm</name>
            <address>47 Canary Point</address>
            <uuid>472412956</uuid>
          </customer>
          <payment>card</payment>
          <carddetails>
            <cardtype>jcb</cardtype>
            <number>3540564668810266</number>
            <contactless>false</contactless>
          </carddetails>
        </invoice>
      </invoices>
    </store>
    <store name="Mita" address="02 Badeau Road">
      <receipts>
        <receipt>
          <total>6032.68</total>
          <datetime>2019-09-13T15:57:00</datetime>
          <payment>cash</payment>
        </receipt>
        <receipt>
          <total>3968</total>
          <datetime>2019-09-13T16:14:00</datetime>
          <payment>card</payment>
          <carddetails>
            <cardtype>jcb</cardtype>
            <number>3546287876201235</number>
            <contactless>false</contactless>
          </carddetails>
        </receipt>
        <receipt>
          <total>8717.26</total>
          <datetime>2019-09-13T13:44:00</datetime>
          <payment>card</payment>
          <carddetails>
            <cardtype>jcb</cardtype>
            <number>3531179498133432</number>
            <contactless>false</contactless>
          </carddetails>
        </receipt>
        <receipt>
          <total>2703.27</total>
          <datetime>2019-09-13T10:22:00</datetime>
          <payment>cash</payment>
        </receipt>
        <receipt>
          <total>9424.06</total>
          <datetime>2019-09-13T10:33:00</datetime>
          <payment>card</payment>
          <carddetails>
            <cardtype>jcb</cardtype>
            <number>3559886023906184</number>
            <contactless>true</contactless>
          </carddetails>
        </receipt>
        <receipt>
          <total>6096.42</total>
          <datetime>2019-09-13T09:56:00</datetime>
          <payment>cash</payment>
        </receipt>
        <receipt>
          <total>5931.08</total>
          <datetime>2019-09-13T13:58:00</datetime>
          <payment>cash</payment>
        </receipt>
        <receipt>
          <total>9788.6</total>
          <datetime>2019-09-13T11:55:00</datetime>
          <payment>card</payment>
          <carddetails>
            <cardtype>jcb</cardtype>
            <number>3587422221611198</number>
            <contactless>true</contactless>
          </carddetails>
        </receipt>
        <receipt>
          <total>4639.32</total>
          <datetime>2019-09-13T13:24:00</datetime>
          <payment>cash</payment>
        </receipt>
        <receipt>
          <total>1611.46</total>
          <datetime>2019-09-13T11:27:00</datetime>
          <payment>cash</payment>
        </receipt>
        <receipt>
          <total>4772.64</total>
          <datetime>2019-09-13T15:16:00</datetime>
          <payment>cash</payment>
        </receipt>
        <receipt>
          <total>6077.43</total>
          <datetime>2019-09-13T10:06:00</datetime>
          <payment>card</payment>
          <carddetails>
            <cardtype>china-unionpay</cardtype>
            <number>5602228068633104</number>
            <contactless>true</contactless>
          </carddetails>
        </receipt>
      </receipts>
      <invoices>
        <invoice>
          <total>16040.14</total>
          <datetime>2019-09-13T11:48:00</datetime>
          <customer>
            <name>Feedmix</name>
            <address>9621 Spenser Alley</address>
            <uuid>839249696</uuid>
          </customer>
          <payment>card</payment>
          <carddetails>
            <cardtype>jcb</cardtype>
            <number>3547901516845586</number>
            <contactless>false</contactless>
          </carddetails>
        </invoice>
        <invoice>
          <total>69978.29</total>
          <datetime>2019-09-13T14:18:00</datetime>
          <customer>
            <name>Kamba</name>
            <address>1 Maryland Parkway</address>
            <uuid>985221525</uuid>
          </customer>
          <payment>card</payment>
          <carddetails>
            <cardtype>maestro</cardtype>
            <number>6762389541501195</number>
            <contactless>true</contactless>
          </carddetails>
        </invoice>
        <invoice>
          <total>88724.18</total>
          <datetime>2019-09-13T09:47:00</datetime>
          <customer>
            <name>Kamba</name>
            <address>1 Maryland Parkway</address>
            <uuid>985221525</uuid>
          </customer>
          <payment>card</payment>
          <carddetails>
            <cardtype>bankcard</cardtype>
            <number>5602210544174010</number>
            <contactless>false</contactless>
          </carddetails>
        </invoice>
        <invoice>
          <total>85106.44</total>
          <datetime>2019-09-13T14:32:00</datetime>
          <customer>
            <name>Fiveclub</name>
            <address>085 Grayhawk Lane</address>
            <uuid>432573080</uuid>
          </customer>
          <payment>card</payment>
          <carddetails>
            <cardtype>americanexpress</cardtype>
            <number>374283916093594</number>
            <contactless>true</contactless>
          </carddetails>
        </invoice>
        <invoice>
          <total>74986.95</total>
          <datetime>2019-09-13T16:11:00</datetime>
          <customer>
            <name>Izio</name>
            <address>57 Esker Circle</address>
            <uuid>981958422</uuid>
          </customer>
          <payment>card</payment>
          <carddetails>
            <cardtype>visa-electron</cardtype>
            <number>4508021595803292</number>
            <contactless>false</contactless>
          </carddetails>
        </invoice>
        <invoice>
          <total>42860.37</total>
          <datetime>2019-09-13T15:45:00</datetime>
          <customer>
            <name>Innojam</name>
            <address>35190 Northridge Street</address>
            <uuid>445132775</uuid>
          </customer>
          <payment>cash</payment>
        </invoice>
        <invoice>
          <total>43778.87</total>
          <datetime>2019-09-13T07:36:00</datetime>
          <customer>
            <name>Innojam</name>
            <address>35190 Northridge Street</address>
            <uuid>445132775</uuid>
          </customer>
          <payment>card</payment>
          <carddetails>
            <cardtype>jcb</cardtype>
            <number>3573564296237593</number>
            <contactless>false</contactless>
          </carddetails>
        </invoice>
        <invoice>
          <total>63762.85</total>
          <datetime>2019-09-13T12:55:00</datetime>
          <customer>
            <name>Kimia</name>
            <address>9 Oak Valley Point</address>
            <uuid>476160250</uuid>
          </customer>
          <payment>cash</payment>
        </invoice>
      </invoices>
    </store>
    <store name="Jamia" address="124 Monterey Junction">
      <receipts>
        <receipt>
          <total>1392.91</total>
          <datetime>2019-09-13T14:27:00</datetime>
          <payment>cash</payment>
        </receipt>
        <receipt>
          <total>280.86</total>
          <datetime>2019-09-13T16:10:00</datetime>
          <payment>cash</payment>
        </receipt>
        <receipt>
          <total>3370.8</total>
          <datetime>2019-09-13T15:55:00</datetime>
          <payment>card</payment>
          <carddetails>
            <cardtype>bankcard</cardtype>
            <number>5602214935836211</number>
            <contactless>true</contactless>
          </carddetails>
        </receipt>
        <receipt>
          <total>7544.78</total>
          <datetime>2019-09-13T17:20:00</datetime>
          <payment>card</payment>
          <carddetails>
            <cardtype>mastercard</cardtype>
            <number>5100137063330698</number>
            <contactless>false</contactless>
          </carddetails>
        </receipt>
        <receipt>
          <total>4683.69</total>
          <datetime>2019-09-13T13:39:00</datetime>
          <payment>card</payment>
          <carddetails>
            <cardtype>jcb</cardtype>
            <number>3553547094793846</number>
            <contactless>true</contactless>
          </carddetails>
        </receipt>
        <receipt>
          <total>8831.28</total>
          <datetime>2019-09-13T11:47:00</datetime>
          <payment>card</payment>
          <carddetails>
            <cardtype>jcb</cardtype>
            <number>3539938882798049</number>
            <contactless>true</contactless>
          </carddetails>
        </receipt>
        <receipt>
          <total>5264.35</total>
          <datetime>2019-09-13T10:52:00</datetime>
          <payment>cash</payment>
        </receipt>
        <receipt>
          <total>6440.95</total>
          <datetime>2019-09-13T14:41:00</datetime>
          <payment>cash</payment>
        </receipt>
        <receipt>
          <total>8914.56</total>
          <datetime>2019-09-13T17:59:00</datetime>
          <payment>card</payment>
          <carddetails>
            <cardtype>visa-electron</cardtype>
            <number>4844762213017681</number>
            <contactless>false</contactless>
          </carddetails>
        </receipt>
        <receipt>
          <total>4649.31</total>
          <datetime>2019-09-13T10:01:00</datetime>
          <payment>cash</payment>
        </receipt>
        <receipt>
          <total>5869.96</total>
          <datetime>2019-09-13T11:43:00</datetime>
          <payment>card</payment>
          <carddetails>
            <cardtype>jcb</cardtype>
            <number>3553547094793846</number>
            <contactless>true</contactless>
          </carddetails>
        </receipt>
        <receipt>
          <total>55.7</total>
          <datetime>2019-09-13T12:10:00</datetime>
          <payment>cash</payment>
        </receipt>
      </receipts>
      <invoices>
        <invoice>
          <total>15761</total>
          <datetime>2019-09-13T13:28:00</datetime>
          <customer>
            <name>Innojam</name>
            <address>35190 Northridge Street</address>
            <uuid>445132775</uuid>
          </customer>
          <payment>cash</payment>
        </invoice>
        <invoice>
          <total>19729.12</total>
          <datetime>2019-09-13T11:38:00</datetime>
          <customer>
            <name>Jabbersphere</name>
            <address>564 Glendale Terrace</address>
            <uuid>511790124</uuid>
          </customer>
          <payment>card</payment>
          <carddetails>
            <cardtype>visa-electron</cardtype>
            <number>4844762213017681</number>
            <contactless>false</contactless>
          </carddetails>
        </invoice>
        <invoice>
          <total>92247.29</total>
          <datetime>2019-09-13T16:42:00</datetime>
          <customer>
            <name>Blognation</name>
            <address>627 Nova Way</address>
            <uuid>722497529</uuid>
          </customer>
          <payment>cash</payment>
        </invoice>
        <invoice>
          <total>70755.09</total>
          <datetime>2019-09-13T06:40:00</datetime>
          <customer>
            <name>Blognation</name>
            <address>627 Nova Way</address>
            <uuid>722497529</uuid>
          </customer>
          <payment>cash</payment>
        </invoice>
        <invoice>
          <total>65757.01</total>
          <datetime>2019-09-13T09:42:00</datetime>
          <customer>
            <name>Voomm</name>
            <address>47 Canary Point</address>
            <uuid>472412956</uuid>
          </customer>
          <payment>card</payment>
          <carddetails>
            <cardtype>jcb</cardtype>
            <number>3566075582373876</number>
            <contactless>false</contactless>
          </carddetails>
        </invoice>
        <invoice>
          <total>87429.9</total>
          <datetime>2019-09-13T13:09:00</datetime>
          <customer>
            <name>Voolith</name>
            <address>1 Forest Dale Hill</address>
            <uuid>206320288</uuid>
          </customer>
          <payment>cash</payment>
        </invoice>
        <invoice>
          <total>45604.61</total>
          <datetime>2019-09-13T12:26:00</datetime>
          <customer>
            <name>Centimia</name>
            <address>25 Manitowish Road</address>
            <uuid>441046281</uuid>
          </customer>
          <payment>cash</payment>
        </invoice>
        <invoice>
          <total>56155.48</total>
          <datetime>2019-09-13T06:17:00</datetime>
          <customer>
            <name>Kimia</name>
            <address>9 Oak Valley Point</address>
            <uuid>476160250</uuid>
          </customer>
          <payment>card</payment>
          <carddetails>
            <cardtype>jcb</cardtype>
            <number>3536133673088684</number>
            <contactless>false</contactless>
          </carddetails>
        </invoice>
      </invoices>
    </store>
  </stores>
</company>